asyncqt/__init__.py
asyncqt/_common.py
asyncqt/_unix.py
asyncqt/_windows.py
asyncqt-0.7.0.dist-info/LICENSE
asyncqt-0.7.0.dist-info/METADATA
asyncqt-0.7.0.dist-info/WHEEL
asyncqt-0.7.0.dist-info/top_level.txt
asyncqt-0.7.0.dist-info/RECORD
