Metadata-Version: 2.1
Name: asyncqt
Version: 0.7.0
Summary: Implementation of the PEP 3156 Event-Loop with Qt.
Home-page: https://github.com/gmarull/asyncqt
Author: G, e, r, a, r, d,  , M, a, r, u, l, l, -, P, a, r, e, t, a, s, M, a, r, k,  , H, a, r, v, i, s, t, o, n, A, r, v, e,  , K, n, u, d, s, e, n
Author-email: gerard@teslabs.com, mark.harviston@gmail.com, arve.knudsen@gmail.com
License: BSD
Keywords: Qt,asyncio
Platform: UNKNOWN
Classifier: Development Status :: 3 - Alpha
Classifier: License :: OSI Approved :: BSD License
Classifier: Intended Audience :: Developers
Classifier: Operating System :: Microsoft :: Windows
Classifier: Operating System :: MacOS :: MacOS X
Classifier: Operating System :: POSIX
Classifier: Programming Language :: Python :: 3.5
Classifier: Programming Language :: Python :: 3.6
Classifier: Programming Language :: Python :: 3.7
Classifier: Programming Language :: Python :: 3 :: Only
Classifier: Environment :: X11 Applications :: Qt
